{
  "dataset_path": "C:\\Users\\arfdd\\coding\\fiap-tech-challenge-fase-1\\train_model\\datasets\\dataset.csv",
  "experiments": [
    {
      "name": "exp1",
      "pop_size": 8,
      "generations": 3,
      "cx_prob": 0.8,
      "mut_prob": 0.1,
      "seed": 1
    },
    {
      "name": "exp2",
      "pop_size": 8,
      "generations": 3,
      "cx_prob": 0.8,
      "mut_prob": 0.3,
      "seed": 2
    },
    {
      "name": "exp3",
      "pop_size": 12,
      "generations": 3,
      "cx_prob": 0.8,
      "mut_prob": 0.1,
      "seed": 3
    }
  ],
  "fitness_weights": {
    "recall": 0.6,
    "specificity": 0.2,
    "f1": 0.2,
    "fairness_penalty": 0.5
  },
  "results_by_model": {
    "RandomForestClassifier": {
      "exp1": {
        "best_params": {
          "n_estimators": 185,
          "max_depth": 21,
          "min_samples_split": 9,
          "min_samples_leaf": 3,
          "max_features": 0.687
        },
        "best_fitness": 0.5320030868387852,
        "validation_metrics": {
          "recall": 0.5427631578947368,
          "specificity": 0.5337837837837838,
          "f1": 0.5436573311367381,
          "fairness_penalty": 0.01828606176432257
        },
        "history": [
          0.5307894282199057,
          0.5320030868387852,
          0.5320030868387852
        ],
        "config": {
          "pop_size": 8,
          "generations": 3,
          "cx_prob": 0.8,
          "mut_prob": 0.1,
          "seed": 1
        }
      },
      "exp2": {
        "best_params": {
          "n_estimators": 163,
          "max_depth": 27,
          "min_samples_split": 2,
          "min_samples_leaf": 1,
          "max_features": 0.6585
        },
        "best_fitness": 0.5371288970475068,
        "validation_metrics": {
          "recall": 0.5394736842105263,
          "specificity": 0.5574324324324325,
          "f1": 0.5475792988313857,
          "fairness_penalty": 0.015115319463145593
        },
        "history": [
          0.5276697472516072,
          0.5276697472516072,
          0.5371288970475068
        ],
        "config": {
          "pop_size": 8,
          "generations": 3,
          "cx_prob": 0.8,
          "mut_prob": 0.3,
          "seed": 2
        }
      },
      "exp3": {
        "best_params": {
          "n_estimators": 221,
          "max_depth": 27,
          "min_samples_split": 3,
          "min_samples_leaf": 2,
          "max_features": 0.8308
        },
        "best_fitness": 0.5550641876345416,
        "validation_metrics": {
          "recall": 0.569078947368421,
          "specificity": 0.5472972972972973,
          "f1": 0.5662847790507365,
          "fairness_penalty": 0.01819919211223553
        },
        "history": [
          0.5550641876345416,
          0.5550641876345416,
          0.5550641876345416
        ],
        "config": {
          "pop_size": 12,
          "generations": 3,
          "cx_prob": 0.8,
          "mut_prob": 0.1,
          "seed": 3
        }
      }
    },
    "LogisticRegression": {
      "exp1": {
        "best_params": {
          "C": 0.1885,
          "penalty": "l1",
          "solver": "saga",
          "class_weight": null,
          "max_iter": 435
        },
        "best_fitness": 0.50074775128421,
        "validation_metrics": {
          "recall": 0.5756578947368421,
          "specificity": 0.4155405405405405,
          "f1": 0.5368098159509203,
          "fairness_penalty": 0.07023411371237465
        },
        "history": [
          0.47806142248746564,
          0.47806142248746564,
          0.50074775128421
        ],
        "config": {
          "pop_size": 8,
          "generations": 3,
          "cx_prob": 0.8,
          "mut_prob": 0.1,
          "seed": 1
        }
      },
      "exp2": {
        "best_params": {
          "C": 0.367,
          "penalty": "l1",
          "solver": "saga",
          "class_weight": "balanced",
          "max_iter": 940
        },
        "best_fitness": 0.46090262275316857,
        "validation_metrics": {
          "recall": 0.5263157894736842,
          "specificity": 0.5067567567567568,
          "f1": 0.5245901639344263,
          "fairness_penalty": 0.12231247013855706
        },
        "history": [
          0.46090262275316857,
          0.46090262275316857,
          0.46090262275316857
        ],
        "config": {
          "pop_size": 8,
          "generations": 3,
          "cx_prob": 0.8,
          "mut_prob": 0.3,
          "seed": 2
        }
      },
      "exp3": {
        "best_params": {
          "C": 0.1613,
          "penalty": "l1",
          "solver": "saga",
          "class_weight": null,
          "max_iter": 256
        },
        "best_fitness": 0.511896547732836,
        "validation_metrics": {
          "recall": 0.5855263157894737,
          "specificity": 0.4155405405405405,
          "f1": 0.5435114503816794,
          "fairness_penalty": 0.062459279850584304
        },
        "history": [
          0.471051556425196,
          0.48799915064217125,
          0.511896547732836
        ],
        "config": {
          "pop_size": 12,
          "generations": 3,
          "cx_prob": 0.8,
          "mut_prob": 0.1,
          "seed": 3
        }
      }
    },
    "KNeighborsClassifier": {
      "exp1": {
        "best_params": {
          "n_neighbors": 3,
          "weights": "distance",
          "p": 2
        },
        "best_fitness": 0.5369119078215189,
        "validation_metrics": {
          "recall": 0.5361842105263158,
          "specificity": 0.5709459459459459,
          "f1": 0.5488215488215489,
          "fairness_penalty": 0.017504234895539206
        },
        "history": [
          0.5175364830166715,
          0.5369119078215189,
          0.5369119078215189
        ],
        "config": {
          "pop_size": 8,
          "generations": 3,
          "cx_prob": 0.8,
          "mut_prob": 0.1,
          "seed": 1
        }
      },
      "exp2": {
        "best_params": {
          "n_neighbors": 9,
          "weights": "uniform",
          "p": 2
        },
        "best_fitness": 0.5456027761082889,
        "validation_metrics": {
          "recall": 0.5460526315789473,
          "specificity": 0.543918918918919,
          "f1": 0.5487603305785124,
          "fairness_penalty": 0.0011293054771316369
        },
        "history": [
          0.5379452908676381,
          0.5379452908676381,
          0.5456027761082889
        ],
        "config": {
          "pop_size": 8,
          "generations": 3,
          "cx_prob": 0.8,
          "mut_prob": 0.3,
          "seed": 2
        }
      },
      "exp3": {
        "best_params": {
          "n_neighbors": 9,
          "weights": "uniform",
          "p": 2
        },
        "best_fitness": 0.5456027761082889,
        "validation_metrics": {
          "recall": 0.5460526315789473,
          "specificity": 0.543918918918919,
          "f1": 0.5487603305785124,
          "fairness_penalty": 0.0011293054771316369
        },
        "history": [
          0.5183376171781592,
          0.5456027761082889,
          0.5456027761082889
        ],
        "config": {
          "pop_size": 12,
          "generations": 3,
          "cx_prob": 0.8,
          "mut_prob": 0.1,
          "seed": 3
        }
      }
    },
    "ExtraTreesClassifier": {
      "exp1": {
        "best_params": {
          "n_estimators": 244,
          "max_depth": 17,
          "min_samples_split": 9,
          "min_samples_leaf": 4,
          "max_features": 0.8521
        },
        "best_fitness": 0.4806330337955331,
        "validation_metrics": {
          "recall": 0.46381578947368424,
          "specificity": 0.5641891891891891,
          "f1": 0.4912891986062718,
          "fairness_penalty": 0.01750423489553926
        },
        "history": [
          0.4806330337955331,
          0.4806330337955331,
          0.4806330337955331
        ],
        "config": {
          "pop_size": 8,
          "generations": 3,
          "cx_prob": 0.8,
          "mut_prob": 0.1,
          "seed": 1
        }
      },
      "exp2": {
        "best_params": {
          "n_estimators": 163,
          "max_depth": 14,
          "min_samples_split": 7,
          "min_samples_leaf": 1,
          "max_features": 0.9097
        },
        "best_fitness": 0.5036369052183043,
        "validation_metrics": {
          "recall": 0.4901315789473684,
          "specificity": 0.543918918918919,
          "f1": 0.5068027210884354,
          "fairness_penalty": 0.001172740303175046
        },
        "history": [
          0.4793076309243358,
          0.48007358824239243,
          0.5036369052183043
        ],
        "config": {
          "pop_size": 8,
          "generations": 3,
          "cx_prob": 0.8,
          "mut_prob": 0.3,
          "seed": 2
        }
      },
      "exp3": {
        "best_params": {
          "n_estimators": 118,
          "max_depth": 18,
          "min_samples_split": 3,
          "min_samples_leaf": 1,
          "max_features": 0.9362
        },
        "best_fitness": 0.5073301081775707,
        "validation_metrics": {
          "recall": 0.5131578947368421,
          "specificity": 0.5236486486486487,
          "f1": 0.519134775374376,
          "fairness_penalty": 0.01824262693827905
        },
        "history": [
          0.5003093601621227,
          0.5073301081775707,
          0.5073301081775707
        ],
        "config": {
          "pop_size": 12,
          "generations": 3,
          "cx_prob": 0.8,
          "mut_prob": 0.1,
          "seed": 3
        }
      }
    }
  },
  "ranking": [
    {
      "model_name": "RandomForestClassifier",
      "best_experiment": "exp3",
      "best_fitness": 0.5550641876345416,
      "best_params": {
        "n_estimators": 221,
        "max_depth": 27,
        "min_samples_split": 3,
        "min_samples_leaf": 2,
        "max_features": 0.8308
      }
    },
    {
      "model_name": "KNeighborsClassifier",
      "best_experiment": "exp2",
      "best_fitness": 0.5456027761082889,
      "best_params": {
        "n_neighbors": 9,
        "weights": "uniform",
        "p": 2
      }
    },
    {
      "model_name": "LogisticRegression",
      "best_experiment": "exp3",
      "best_fitness": 0.511896547732836,
      "best_params": {
        "C": 0.1613,
        "penalty": "l1",
        "solver": "saga",
        "class_weight": null,
        "max_iter": 256
      }
    },
    {
      "model_name": "ExtraTreesClassifier",
      "best_experiment": "exp3",
      "best_fitness": 0.5073301081775707,
      "best_params": {
        "n_estimators": 118,
        "max_depth": 18,
        "min_samples_split": 3,
        "min_samples_leaf": 1,
        "max_features": 0.9362
      }
    }
  ],
  "best_overall": {
    "model_name": "RandomForestClassifier",
    "best_experiment": "exp3",
    "best_fitness": 0.5550641876345416,
    "best_params": {
      "n_estimators": 221,
      "max_depth": 27,
      "min_samples_split": 3,
      "min_samples_leaf": 2,
      "max_features": 0.8308
    },
    "export": {
      "artifact_path": "C:\\Users\\arfdd\\coding\\fiap-tech-challenge-fase-1\\backend\\model\\lung_cancer_classifier.joblib",
      "metadata_path": "C:\\Users\\arfdd\\coding\\fiap-tech-challenge-fase-1\\backend\\model\\lung_cancer_classifier.metadata.json",
      "threshold_summary": {
        "threshold": 0.15,
        "precision": 0.5075125208681135,
        "recall": 1.0,
        "specificity": 0.0033783783783783786,
        "f1": 0.6733111849390919
      },
      "test_metrics": {
        "accuracy": 0.505,
        "precision": 0.505,
        "recall": 1.0,
        "specificity": 0.0,
        "f1": 0.6710963455149501,
        "tp": 303,
        "tn": 0,
        "fp": 297,
        "fn": 0,
        "threshold": 0.15
      }
    }
  }
}